oxautocompletion/__init__.py
oxautocompletion/main.py
oxautocompletion-0.0.2.dist-info/METADATA
oxautocompletion-0.0.2.dist-info/WHEEL
oxautocompletion-0.0.2.dist-info/top_level.txt
oxautocompletion-0.0.2.dist-info/RECORD
