Metadata-Version: 2.1
Name: oxautocompletion
Version: 0.0.2
Summary: A Handy Package to add Auto-Completion
Author: 0x68616469
Keywords: auto,completion
Classifier: Development Status :: 4 - Beta
Classifier: Intended Audience :: Developers
Classifier: Programming Language :: Python :: 3
Classifier: Operating System :: Unix
Classifier: Operating System :: MacOS :: MacOS X
Classifier: Operating System :: Microsoft :: Windows
Requires-Dist: oxansi
